{"ranking":[{"name":"Afghanistan","value":108451},{"name":"Albania","value":36733},{"name":"Algeria","value":122236},{"name":"Andorra","value":12294},{"name":"Angola","value":65695},{"name":"Argentina","value":185434},{"name":"Armenia","value":92400},{"name":"Australia","value":382593},{"name":"Austria","value":325979},{"name":"Azerbaijan","value":134542},{"name":"Bahrain","value":19467},{"name":"Bangladesh","value":200241},{"name":"Belarus","value":92910},{"name":"Belgium","value":315411},{"name":"Benin","value":58951},{"name":"Bhutan","value":11135},{"name":"Bolivia","value":67225},{"name":"Bosnia and Herz.","value":372},{"name":"Botswana","value":16280},{"name":"Brazil","value":242035},{"name":"Bulgaria","value":216034},{"name":"Burkina Faso","value":4366},{"name":"Burundi","value":13650},{"name":"Cambodia","value":59555},{"name":"Cameroon","value":123849},{"name":"Canada","value":388469},{"name":"Chad","value":6012},{"name":"Chile","value":140973},{"name":"China","value":335084},{"name":"Colombia","value":134202},{"name":"Congo","value":26677},{"name":"Croatia","value":139468},{"name":"Cuba","value":93842},{"name":"Cyprus","value":89692},{"name":"Czechia","value":312632},{"name":"Denmark","value":259425},{"name":"Dominican Rep.","value":39594},{"name":"Ecuador","value":102535},{"name":"Egypt","value":224107},{"name":"El Salvador","value":55504},{"name":"Estonia","value":115357},{"name":"Ethiopia","value":283723},{"name":"Finland","value":250295},{"name":"France","value":525950},{"name":"Georgia","value":139870},{"name":"Germany","value":601105},{"name":"Ghana","value":242662},{"name":"Greece","value":161581},{"name":"Guatemala","value":73672},{"name":"Honduras","value":37034},{"name":"Hong Kong","value":184976},{"name":"Hungary","value":203515},{"name":"Iceland","value":58924},{"name":"India","value":265660},{"name":"Indonesia","value":348495},{"name":"Iran","value":253207},{"name":"Iraq","value":55435},{"name":"Ireland","value":173009},{"name":"Israel","value":217206},{"name":"Italy","value":365282},{"name":"Jamaica","value":62118},{"name":"Japan","value":491527},{"name":"Jordan","value":48863},{"name":"Kazakhstan","value":77984},{"name":"Kenya","value":366488},{"name":"Kuwait","value":16451},{"name":"Laos","value":6844},{"name":"Latvia","value":60823},{"name":"Lithuania","value":87326},{"name":"Luxembourg","value":59957},{"name":"Madagascar","value":111857},{"name":"Malawi","value":40506},{"name":"Malaysia","value":146266},{"name":"Maldives","value":9697},{"name":"Mali","value":13019},{"name":"Malta","value":34923},{"name":"Mauritania","value":5958},{"name":"Mauritius","value":29191},{"name":"Mexico","value":168609},{"name":"Moldova","value":45465},{"name":"Mongolia","value":34174},{"name":"Montenegro","value":49350},{"name":"Morocco","value":244138},{"name":"Mozambique","value":34947},{"name":"Myanmar","value":93400},{"name":"Namibia","value":13975},{"name":"Nepal","value":165199},{"name":"Netherlands","value":435181},{"name":"New Zealand","value":162178},{"name":"Nicaragua","value":100286},{"name":"Nigeria","value":208537},{"name":"Norway","value":272786},{"name":"Oman","value":20582},{"name":"Pakistan","value":183579},{"name":"Palestine","value":80956},{"name":"Panama","value":29420},{"name":"Paraguay","value":57422},{"name":"Peru","value":99441},{"name":"Philippines","value":325602},{"name":"Poland","value":342888},{"name":"Portugal","value":254453},{"name":"Qatar","value":23859},{"name":"Romania","value":175413},{"name":"Russia","value":245133},{"name":"Rwanda","value":215699},{"name":"San Marino","value":2081},{"name":"Saudi Arabia","value":38151},{"name":"Senegal","value":53073},{"name":"Serbia","value":151174},{"name":"Sierra Leone","value":6150},{"name":"Singapore","value":211776},{"name":"Slovakia","value":125836},{"name":"Slovenia","value":112618},{"name":"South Africa","value":144142},{"name":"South Korea","value":313328},{"name":"Spain","value":376330},{"name":"Sri Lanka","value":178138},{"name":"Sudan","value":37999},{"name":"Sweden","value":312056},{"name":"Switzerland","value":402553},{"name":"Syria","value":37468},{"name":"Taiwan","value":286899},{"name":"Tanzania","value":86646},{"name":"Thailand","value":198632},{"name":"Tunisia","value":116775},{"name":"Turkey","value":174655},{"name":"Uganda","value":162264},{"name":"Ukraine","value":209481},{"name":"United Arab Emirates","value":250},{"name":"United Kingdom","value":402437},{"name":"United States of America","value":383504},{"name":"Uruguay","value":111716},{"name":"Uzbekistan","value":140369},{"name":"Venezuela","value":119392},{"name":"Vietnam","value":215924},{"name":"Yemen","value":52857},{"name":"Zambia","value":45345},{"name":"Zambia","value":49423}]}
